PyPacer/CallablePacer.py
PyPacer/__init__.py
pypacer-1.0.dist-info/METADATA
pypacer-1.0.dist-info/WHEEL
pypacer-1.0.dist-info/licenses/LICENSE
pypacer-1.0.dist-info/RECORD
